{
  "title": "Suspicious Usage of netcat",
  "description": "Detects execution of potentially suspicious binary netcat.",
  "query": "('Log Source' = 'SOC Linux Syslog Logs' or 'Log Source' = 'Linux Secure Logs' or 'Log Source' = 'Linux Syslog Logs' or 'Log Source' = 'Linux Audit Logs') and (('Process Name' = 'netcat'))",
  "sigma_id": "d68b1276-c40c-4505-a5dc-c822ea0b2eb3",
  "level": "low",
  "stig_category": "CAT III",
  "tags": [
    "attack.execution",
    "attack.t1204"
  ],
  "mitre_attack": {
    "tactics": [
      "execution"
    ],
    "techniques": [
      "T1204"
    ]
  },
  "logsource": {
    "product": "linux",
    "service": "audit",
    "candidates": [
      "SOC Linux Syslog Logs",
      "Linux Secure Logs",
      "Linux Syslog Logs",
      "Linux Audit Logs"
    ]
  }
}